README.rst
setup.py
adapay_core/__init__.py
adapay_core/api_request.py
adapay_core/log_util.py
adapay_core/param_handler.py
adapay_core/rsa_utils.py
adapay_core.egg-info/PKG-INFO
adapay_core.egg-info/SOURCES.txt
adapay_core.egg-info/dependency_links.txt
adapay_core.egg-info/requires.txt
adapay_core.egg-info/top_level.txt