Metadata-Version: 1.1
Name: adapay-core
Version: 1.2.0
Summary: common utils of adapay sdk
Home-page: https://www.adapay.tech/
Author: adapay developers
Author-email: hi@adapay.tech
License: UNKNOWN
Platform: UNKNOWN
Classifier: Development Status :: 4 - Beta
Classifier: Intended Audience :: Developers
Classifier: Topic :: Software Development :: Build Tools
Classifier: License :: OSI Approved :: MIT License
Classifier: Programming Language :: Python
Classifier: Programming Language :: Python :: 3.5
Classifier: Programming Language :: Python :: 3.6
Classifier: Programming Language :: Python :: 3.7
